hexsticker/__init__.py
hexsticker/cli.py
hexsticker/create.py
hexsticker/exception.py
hexsticker-1.2.1.dist-info/LICENSE
hexsticker-1.2.1.dist-info/METADATA
hexsticker-1.2.1.dist-info/WHEEL
hexsticker-1.2.1.dist-info/entry_points.txt
hexsticker-1.2.1.dist-info/top_level.txt
hexsticker-1.2.1.dist-info/RECORD
