Metadata-Version: 2.1
Name: hexsticker
Version: 1.2.1
Summary: Convert any image to image that conforms with hexagon stickers standard.
Home-page: https://github.com/fridex/hexsticker
Author: Fridolin Pokorny
Author-email: fridolin.pokorny@gmail.com
Maintainer: Fridolin Pokorny
Maintainer-email: fridolin.pokorny@gmail.com
License: GPLv2
Keywords: hexagon stickers hexagon-stickers
Classifier: Environment :: Console
Classifier: Intended Audience :: End Users/Desktop
Classifier: License :: OSI Approved :: GNU General Public License v2 (GPLv2)
Classifier: Operating System :: OS Independent
Classifier: Programming Language :: Python :: 3
Classifier: Programming Language :: Python :: 3.6
Classifier: Programming Language :: Python :: 3.7
Classifier: Programming Language :: Python :: 3.8
Classifier: Programming Language :: Python :: 3.9
Classifier: Programming Language :: Python :: 3 :: Only
Classifier: Programming Language :: Python :: Implementation :: CPython
Classifier: Programming Language :: Python :: Implementation :: PyPy
Classifier: Topic :: Multimedia :: Graphics
Classifier: Topic :: Multimedia :: Graphics :: Graphics Conversion
Classifier: Topic :: Multimedia :: Graphics :: Presentation
Classifier: Topic :: Utilities
License-File: LICENSE
Requires-Dist: click
Requires-Dist: pillow>=10.0.0
